netbek/__init__.py
netbek/periodic_table/__init__.py
netbek/periodic_table/data.py
netbek/periodic_table/jinja/macros/nb_pt_axis_cell.jinja2
netbek/periodic_table/jinja/macros/nb_pt_blockholder_element_cell.jinja2
netbek/periodic_table/jinja/macros/nb_pt_element_cell.jinja2
netbek/periodic_table/jinja/macros/nb_pt_empty_cell.jinja2
netbek/periodic_table/jinja/macros/nb_pt_legend.jinja2
netbek/periodic_table/jinja/macros/nb_pt_table_18.jinja2
netbek_periodic_table-0.2.3.dist-info/METADATA
netbek_periodic_table-0.2.3.dist-info/WHEEL
netbek_periodic_table-0.2.3.dist-info/licenses/LICENSE
netbek_periodic_table-0.2.3.dist-info/RECORD
