Metadata-Version: 2.4
Name: netbek-periodic-table
Version: 0.2.3
Summary: Periodic table with responsive layout
License-File: LICENSE
Requires-Python: >=3.10
Requires-Dist: jinja2>=3.1.6
